the_judge/__init__.py
the_judge-1.0.0.dist-info/METADATA
the_judge-1.0.0.dist-info/WHEEL
the_judge-1.0.0.dist-info/top_level.txt
the_judge-1.0.0.dist-info/RECORD
