Metadata-Version: 2.4
Name: the-judge
Version: 1.0.0
Summary: A judge for llms
Home-page: https://example.com
Author: Luis
Author-email: luisbeqjamw@gmail.com
Project-URL: Docs, https://docs.example.com
Classifier: Programming Language :: Python :: 3
Classifier: License :: OSI Approved :: MIT License
Classifier: Operating System :: OS Independent
